MANIFEST.in
README.md
setup.py
numparse164/__init__.py
numparse164/uk.py
numparse164.egg-info/PKG-INFO
numparse164.egg-info/SOURCES.txt
numparse164.egg-info/dependency_links.txt
numparse164.egg-info/not-zip-safe
numparse164.egg-info/requires.txt
numparse164.egg-info/top_level.txt