Metadata-Version: 1.0
Name: numparse164
Version: 0.2
Summary: Parse telephone numbers
Home-page: http://github.com/binzcodes/numparse164
Author: Ryan Binns
Author-email: binz@binz.codes
License: GNU
Platform: UNKNOWN
